funcker/cli/__init__.py
funcker/cli/__main__.py
funcker/cli/main.py
funcker/plug/__init__.py
funcker/plug/main.py
funcker/run/__init__.py
funcker/run/main.py
funcker-0.1.1.dist-info/entry_points.txt
funcker-0.1.1.dist-info/WHEEL
funcker-0.1.1.dist-info/METADATA
funcker-0.1.1.dist-info/RECORD
