Metadata-Version: 2.1
Name: funcker
Version: 0.1.1
Summary: plug and run funcker function
Author: romainprignon
Author-email: pro.rprignon@gmail.com
Requires-Python: >=3.8,<4.0
Classifier: Programming Language :: Python :: 3
Classifier: Programming Language :: Python :: 3.10
Classifier: Programming Language :: Python :: 3.8
Classifier: Programming Language :: Python :: 3.9
Requires-Dist: docker (>=5.0.3,<6.0.0)
Requires-Dist: typer[all] (>=0.4.2,<0.5.0)
